setup.cfg
setup.py
sqlfeedgraphite/__init__.py
sqlfeedgraphite.egg-info/PKG-INFO
sqlfeedgraphite.egg-info/SOURCES.txt
sqlfeedgraphite.egg-info/dependency_links.txt
sqlfeedgraphite.egg-info/requires.txt
sqlfeedgraphite.egg-info/top_level.txt
sqlfeedgraphite.egg-info/zip-safe