Metadata-Version: 1.1
Name: sqlfeedgraphite
Version: 0.2
Summary: https://github.com/orachide/sql-feed-graphite
Home-page: https://github.com/orachide/sql-feed-graphite
Author: Rachide Ouattara
Author-email: ouattchidi@gmail.com
License: BSD
Download-URL: https://github.com/orachide/sql-feed-graphite/archive/0.2.tar.gz
Keywords: SQL Graphite Metrics
Platform: UNKNOWN
